{
    "label": "Mysurvives-Thaumaturge-Macros",
    "entries": {
        "Cursed Effigy": {
            "name": "Cursed Effigy"
        },
        "Divine Disharmony": {
            "name": "Divine Disharmony"
        },
        "Drink from the Chalice": {
            "name": "Drink from the Chalice"
        },
        "Exploit Vulnerability": {
            "name": "Exploit Vulnerability"
        },
        "Force EV": {
            "name": "Force EV"
        },
        "Glimpse Vulnerability": {
            "name": "Glimpse Vulnerability"
        },
        "Intensify Vulnerability": {
            "name": "Intensify Vulnerability"
        },
        "Recall Knowledge (Esoteric Lore)": {
            "name": "Recall Knowledge (Esoteric Lore)"
        },
        "Root to Life": {
            "name": "Root to Life"
        },
        "Share Weakness": {
            "name": "Share Weakness"
        },
        "Twin Weakness": {
            "name": "Twin Weakness"
        }
    }
}